{"id": "Example_026", "path": "/home/james/Documents/Edoc/3Nohtyp/Python_By_Example/Example_026/Example_026.py", "mtime": 1603403381, "size": 882, "hash": "11b385568799fd57ca32a1bec708d36b", "data_mtime": 1603403625, "dependencies": ["builtins"], "suppressed": [], "child_modules": [], "options": {"show_none_errors": true, "disallow_any_expr": false, "ignore_missing_imports": false, "strict_optional_whitelist": null, "disallow_untyped_calls": false, "ignore_errors": false, "disallow_any_generics": false, "no_implicit_optional": false, "disallow_any_decorated": false, "warn_return_any": false, "quick_and_dirty": false, "warn_no_return": true, "platform": "linux", "strict_boolean": false, "check_untyped_defs": false, "disallow_any_unimported": false, "disallow_untyped_defs": false, "follow_imports": "normal", "disallow_any_explicit": false, "strict_optional": false, "disallow_untyped_decorators": false, "disallow_subclassing_any": false}, "dep_prios": [5], "interface_hash": "d64eaeb6dfdf0e9be47228f95b8dba3f", "version_id": "0.560", "ignore_all": false}
